odoo/addons/delivery_package_number_sale_autoworkflow/README.rst
odoo/addons/delivery_package_number_sale_autoworkflow/__init__.py
odoo/addons/delivery_package_number_sale_autoworkflow/__manifest__.py
odoo/addons/delivery_package_number_sale_autoworkflow/models/__init__.py
odoo/addons/delivery_package_number_sale_autoworkflow/models/stock_picking.py
odoo/addons/delivery_package_number_sale_autoworkflow/static/description/icon.png
odoo_addon_delivery_package_number_sale_autoworkflow-15.0.1.0.0.2.dist-info/METADATA
odoo_addon_delivery_package_number_sale_autoworkflow-15.0.1.0.0.2.dist-info/WHEEL
odoo_addon_delivery_package_number_sale_autoworkflow-15.0.1.0.0.2.dist-info/top_level.txt
odoo_addon_delivery_package_number_sale_autoworkflow-15.0.1.0.0.2.dist-info/RECORD
