Metadata-Version: 2.1
Name: odoo-addon-delivery_package_number_sale_autoworkflow
Version: 15.0.1.0.0.2
Requires-Python: >=3.8
Requires-Dist: odoo-addon-delivery_package_number>=15.0dev,<15.1dev
Requires-Dist: odoo-addon-sale_automatic_workflow>=15.0dev,<15.1dev
Requires-Dist: odoo>=15.0a,<15.1dev
Summary: Make modules delivery_package_number and sale_automatic_workflow compatible
Home-page: https://github.com/sygel-technology/sy-sale-workflow
License: AGPL-3
Author: Sygel, Odoo Community Association (OCA)
Author-email: support@odoo-community.org
Classifier: Programming Language :: Python
Classifier: Framework :: Odoo
Classifier: Framework :: Odoo :: 15.0
Classifier: License :: OSI Approved :: GNU Affero General Public License v3
